c4ai_domain_crawler/__init__.py
c4ai_domain_crawler/domain_crawler.py
c4ai_domain_crawler-0.1.dist-info/METADATA
c4ai_domain_crawler-0.1.dist-info/WHEEL
c4ai_domain_crawler-0.1.dist-info/entry_points.txt
c4ai_domain_crawler-0.1.dist-info/top_level.txt
c4ai_domain_crawler-0.1.dist-info/RECORD
